nucbox/__init__.py
nucbox/op.py
nucbox/gui/__init__.py
nucbox/gui/browser/__init__.py
nucbox/gui/browser/__main__.py
nucbox/gui/browser/canvas.py
nucbox/gui/browser/canvas_control.py
nucbox/gui/browser/layers.py
nucbox/gui/browser/main_window.py
nucbox/gui/browser/menubar.py
nucbox/gui/browser/obj_panel.py
nucbox/gui/browser/range_list.py
nucbox/gui/browser/utils.py
nucbox/gui/widgets/about.py
nucbox/simu/__init__.py
nucbox/simu/base.py
nucbox/simu/gem.py
nucbox/simu/nucdyn.py
nucbox/utils/__init__.py
nucbox/utils/genome.py
nucbox/utils/io.py
nucbox/utils/particles.py
nucbox-0.1.1.dist-info/METADATA
nucbox-0.1.1.dist-info/WHEEL
nucbox-0.1.1.dist-info/top_level.txt
nucbox-0.1.1.dist-info/RECORD
