Metadata-Version: 2.1
Name: nucbox
Version: 0.1.1
Summary: Ultra fast chromosome 3D reconstraction.
Author-email: Weize Xu <vet.xwz@gmail.com>
Requires-Python: >=3.8
Requires-Dist: taichi >=1.7.0
Requires-Dist: fire >=0.6.0
Requires-Dist: pandas >=2.0.3
Requires-Dist: vispy >=0.14.2
Requires-Dist: PyQt5 >=5.15.2
Requires-Dist: qdarkgraystyle >=1.0.2
Requires-Dist: h5py >=3.10.0
Requires-Dist: cooler >=0.9.3
Requires-Dist: scikit-learn >=1.3.2
Requires-Dist: matplotlib >=3.7.5
